mojito/__init__.py
mojito/event/EventComposer.py
mojito/event/EventGenerator.py
mojito/event/PropertyEventGenerator.py
mojito/event/__init__.py
mojito/property/DateGenerator.py
mojito/property/FixedValueGenerator.py
mojito/property/NormalNumberGenerator.py
mojito/property/PoissonNumberGenerator.py
mojito/property/PropertyGenerator.py
mojito/property/RandomChoiceGenerator.py
mojito/property/__init__.py
mojito_mock-0.3.0.dist-info/METADATA
mojito_mock-0.3.0.dist-info/RECORD
mojito_mock-0.3.0.dist-info/WHEEL
mojito_mock-0.3.0.dist-info/top_level.txt
