Metadata-Version: 2.1
Name: mojito-mock
Version: 0.3.0
Summary: Mocking temporal data made easy !
Home-page: https://github.com/PPACI/mojito
Author: Pierre Paci
Author-email: 
License: UNKNOWN
Platform: UNKNOWN
Classifier: Programming Language :: Python :: 3
Classifier: License :: OSI Approved :: Apache Software License
Classifier: Topic :: Scientific/Engineering :: Mathematics
Classifier: Topic :: Scientific/Engineering :: Artificial Intelligence
Classifier: Topic :: Scientific/Engineering
Requires-Dist: numpy (==1.13.3)
Requires-Dist: scipy (==1.1.0)
